solentware_base/__init__.py
solentware_base/apsw_database.py
solentware_base/apswdu_database.py
solentware_base/berkeleydb_database.py
solentware_base/berkeleydbdu_database.py
solentware_base/bsddb3_database.py
solentware_base/bsddb3du_database.py
solentware_base/db_tcl.py
solentware_base/db_tkinter_database.py
solentware_base/db_tkinterdu_database.py
solentware_base/dpt_database.py
solentware_base/dptdu_database.py
solentware_base/dptfastload_database.py
solentware_base/gnu_database.py
solentware_base/gnu_module.py
solentware_base/gnudu_database.py
solentware_base/lmdb_database.py
solentware_base/lmdbdu_database.py
solentware_base/modulequery.py
solentware_base/ndbm_database.py
solentware_base/ndbm_module.py
solentware_base/ndbmdu_database.py
solentware_base/sqlite3_database.py
solentware_base/sqlite3du_database.py
solentware_base/unqlite_database.py
solentware_base/unqlitedu_database.py
solentware_base/vedis_database.py
solentware_base/vedisdu_database.py
solentware_base/core/__init__.py
solentware_base/core/_bytebit.py
solentware_base/core/_database.py
solentware_base/core/_databasedu.py
solentware_base/core/_db.py
solentware_base/core/_db_tkinter.py
solentware_base/core/_dbdu.py
solentware_base/core/_dbdu_tkinter.py
solentware_base/core/_dpt.py
solentware_base/core/_lmdb.py
solentware_base/core/_lmdbdu.py
solentware_base/core/_nosql.py
solentware_base/core/_nosqldu.py
solentware_base/core/_sqlite.py
solentware_base/core/_sqlitedu.py
solentware_base/core/bytebit.py
solentware_base/core/constants.py
solentware_base/core/cursor.py
solentware_base/core/filespec.py
solentware_base/core/find.py
solentware_base/core/findvalues.py
solentware_base/core/merge.py
solentware_base/core/record.py
solentware_base/core/recordset.py
solentware_base/core/recordsetbasecursor.py
solentware_base/core/recordsetcursor.py
solentware_base/core/segmentsize.py
solentware_base/core/tree.py
solentware_base/core/where.py
solentware_base/core/wherevalues.py
solentware_base/tools/__init__.py
solentware_base-5.3.dist-info/licenses/LICENCE
solentware_base-5.3.dist-info/METADATA
solentware_base-5.3.dist-info/WHEEL
solentware_base-5.3.dist-info/top_level.txt
solentware_base-5.3.dist-info/RECORD
