Metadata-Version: 2.4
Name: solentware-base
Version: 5.3
Summary: Bitmapped record number databases.
Author-email: Roger Marsh <roger.marsh@solentware.co.uk>
License-Expression: BSD-3-Clause
Project-URL: Homepage, http://www.solentware.co.uk
Project-URL: Repository, https://github.com/RogerMarsh/solentware-base.git
Project-URL: Bug Tracker, https://github.com/RogerMarsh/solentware-base/issues
Classifier: Programming Language :: Python :: 3.9
Classifier: Programming Language :: Python :: 3.10
Classifier: Programming Language :: Python :: 3.11
Classifier: Programming Language :: Python :: 3.12
Classifier: Operating System :: OS Independent
Classifier: Topic :: Database
Classifier: Intended Audience :: Developers
Classifier: Development Status :: 3 - Alpha
License-File: LICENCE
Dynamic: license-file
